iracing_mcp/__init__.py
iracing_mcp/py.typed
iracing_mcp/entrypoints/__init__.py
iracing_mcp/entrypoints/server.py
iflow_mcp_musantro_iracing_mcp-0.1.2.dev3.dist-info/METADATA
iflow_mcp_musantro_iracing_mcp-0.1.2.dev3.dist-info/WHEEL
iflow_mcp_musantro_iracing_mcp-0.1.2.dev3.dist-info/entry_points.txt
iflow_mcp_musantro_iracing_mcp-0.1.2.dev3.dist-info/licenses/LICENSE
iflow_mcp_musantro_iracing_mcp-0.1.2.dev3.dist-info/RECORD
