Metadata-Version: 2.4
Name: iflow-mcp_musantro_iracing-mcp
Version: 0.1.2.dev3
Summary: A model context protocol server to chat with iRacing data.
Author-email: Antonio Rodríguez <hi@musantro.com>
License-Expression: MIT
License-File: LICENSE
Requires-Python: >=3.11.8
Requires-Dist: iracingdataapi>=1.2.2
Requires-Dist: mcp[cli]>=1.6.0
